tox_extra/__init__.py
tox_extra/_version.py
tox_extra/bindep.py
tox_extra/hooks.py
tox_extra-2.2.0.dist-info/licenses/LICENSE
tox_extra-2.2.0.dist-info/METADATA
tox_extra-2.2.0.dist-info/WHEEL
tox_extra-2.2.0.dist-info/entry_points.txt
tox_extra-2.2.0.dist-info/top_level.txt
tox_extra-2.2.0.dist-info/RECORD
