Metadata-Version: 2.4
Name: tox-extra
Version: 2.2.0
Summary: Performs extra checks before or after running
Author-email: Sorin Sbarnea <sorin.sbarnea@gmail.com>
Maintainer-email: Sorin Sbarnea <sorin.sbarnea@gmail.com>
License-Expression: MIT
Project-URL: changelog, https://github.com/tox-dev/tox-extra/releases
Project-URL: homepage, https://github.com/tox-dev/tox-extra
Project-URL: issues, https://github.com/tox-dev/tox-extra/issues
Project-URL: repository, https://github.com/tox-dev/tox-extra
Keywords: git,tox,tox-plugin
Classifier: Development Status :: 5 - Production/Stable
Classifier: Intended Audience :: Developers
Classifier: Framework :: tox
Classifier: Programming Language :: Python
Classifier: Programming Language :: Python :: 3
Classifier: Programming Language :: Python :: 3.9
Classifier: Programming Language :: Python :: 3.10
Classifier: Programming Language :: Python :: 3.11
Classifier: Programming Language :: Python :: 3.12
Classifier: Programming Language :: Python :: 3.13
Classifier: Topic :: Software Development :: Testing
Requires-Python: >=3.9
License-File: LICENSE
Requires-Dist: bindep>2.8.1
Requires-Dist: gitpython
Requires-Dist: packaging
Requires-Dist: tox
Requires-Dist: tox-uv>=1.16.0
Provides-Extra: test
Requires-Dist: coverage[toml]>=6.5.0; extra == "test"
Requires-Dist: pytest-mock>=3.10.0; extra == "test"
Requires-Dist: pytest>=7.2.0; extra == "test"
Requires-Dist: testfixtures>=7.0.3; extra == "test"
Dynamic: license-file
